oscar_elasticsearch/__init__.py
oscar_elasticsearch/exceptions.py
oscar_elasticsearch/search/__init__.py
oscar_elasticsearch/search/apps.py
oscar_elasticsearch/search/backend.py
oscar_elasticsearch/search/config.py
oscar_elasticsearch/search/constants.py
oscar_elasticsearch/search/facets.py
oscar_elasticsearch/search/format.py
oscar_elasticsearch/search/forms.py
oscar_elasticsearch/search/helpers.py
oscar_elasticsearch/search/settings.py
oscar_elasticsearch/search/signal_handlers.py
oscar_elasticsearch/search/signals.py
oscar_elasticsearch/search/suggestions.py
oscar_elasticsearch/search/tests.py
oscar_elasticsearch/search/update.py
oscar_elasticsearch/search/utils.py
oscar_elasticsearch/search/api/__init__.py
oscar_elasticsearch/search/api/autocomplete.py
oscar_elasticsearch/search/api/base.py
oscar_elasticsearch/search/api/category.py
oscar_elasticsearch/search/api/pagination.py
oscar_elasticsearch/search/api/product.py
oscar_elasticsearch/search/api/search.py
oscar_elasticsearch/search/fixtures/catalogue/catalogue.json
oscar_elasticsearch/search/fixtures/search/auth.json
oscar_elasticsearch/search/indexing/__init__.py
oscar_elasticsearch/search/indexing/indexer.py
oscar_elasticsearch/search/indexing/settings.py
oscar_elasticsearch/search/locale/de/LC_MESSAGES/django.mo
oscar_elasticsearch/search/locale/de/LC_MESSAGES/django.po
oscar_elasticsearch/search/locale/en/LC_MESSAGES/django.mo
oscar_elasticsearch/search/locale/en/LC_MESSAGES/django.po
oscar_elasticsearch/search/locale/es/LC_MESSAGES/django.mo
oscar_elasticsearch/search/locale/es/LC_MESSAGES/django.po
oscar_elasticsearch/search/locale/fr/LC_MESSAGES/django.mo
oscar_elasticsearch/search/locale/fr/LC_MESSAGES/django.po
oscar_elasticsearch/search/locale/it/LC_MESSAGES/django.mo
oscar_elasticsearch/search/locale/it/LC_MESSAGES/django.po
oscar_elasticsearch/search/locale/nl/LC_MESSAGES/django.mo
oscar_elasticsearch/search/locale/nl/LC_MESSAGES/django.po
oscar_elasticsearch/search/management/__init__.py
django_oscar_elasticsearch-3.0.0.dist-info/LICENSE
django_oscar_elasticsearch-3.0.0.dist-info/METADATA
django_oscar_elasticsearch-3.0.0.dist-info/WHEEL
django_oscar_elasticsearch-3.0.0.dist-info/namespace_packages.txt
django_oscar_elasticsearch-3.0.0.dist-info/top_level.txt
django_oscar_elasticsearch-3.0.0.dist-info/RECORD
